asgi_typing/__init__.py
asgi_typing/application.py
asgi_typing/http.py
asgi_typing/lifespan.py
asgi_typing/py.typed
asgi_typing/versions.py
asgi_typing/websocket.py
jetblack_asgi_typing-0.4.0.dist-info/LICENSE
jetblack_asgi_typing-0.4.0.dist-info/WHEEL
jetblack_asgi_typing-0.4.0.dist-info/METADATA
jetblack_asgi_typing-0.4.0.dist-info/RECORD
