Metadata-Version: 2.1
Name: jetblack-asgi-typing
Version: 0.4.0
Summary: Just the types for ASGI
Home-page: https://github.com/rob-blackbourn/jetblack-asgi-typing
License: Apache-2.0
Author: Rob Blackbourn
Author-email: rob.blackbourn@gmail.com
Requires-Python: >=3.8,<4.0
Classifier: License :: OSI Approved :: Apache Software License
Classifier: Programming Language :: Python :: 3
Classifier: Programming Language :: Python :: 3.8
Classifier: Programming Language :: Python :: 3.9
Project-URL: Repository, https://github.com/rob-blackbourn/jetblack-asgi-typing
